MANIFEST.in
README.md
linkedin.py
setup.py
linkedin.egg-info/PKG-INFO
linkedin.egg-info/SOURCES.txt
linkedin.egg-info/dependency_links.txt
linkedin.egg-info/requires.txt
linkedin.egg-info/top_level.txt