Metadata-Version: 1.0
Name: linkedin
Version: 0.1.0
Summary: A Python Library to interface with LinkedIn API, OAuth and JSON responses
Home-page: https://github.com/michaelhelmick/linkedin/
Author: Mike Helmick
Author-email: mikehelmick@me.com
License: MIT License
Download-URL: https://github.com/michaelhelmick/linkedin/zipball/master
Keywords: python linkedin json oauth api
Platform: UNKNOWN
Classifier: Development Status :: 4 - Beta
Classifier: Intended Audience :: Developers
Classifier: License :: OSI Approved :: MIT License
Classifier: Topic :: Software Development :: Libraries :: Python Modules
Classifier: Topic :: Communications :: Chat
Classifier: Topic :: Internet
